didall/__init__.py
didall/didallclient.py
didall/message_generation.py
didall/short_term_key_generater.py
didall/simple_node.py
didall/simple_node_session.py
didall/simple_wss_wraper.py
didall/wss_message_client.py
didall/wss_message_sdk.py
didall/utils/__init__.py
didall/utils/crypto_tool.py
didall/utils/did_generate.py
didall/utils/did_verify.py
didall/utils/log_base.py
tests/__init__.py
tests/run_all_case.py
tests/run_one_case.py
tests/test_did_gen_verify.py
tests/test_http_did_case.py
tests/test_short_term_key.py
tests/test_wss_message_client.py
didall-0.1.5.dist-info/LICENSE
didall-0.1.5.dist-info/METADATA
didall-0.1.5.dist-info/WHEEL
didall-0.1.5.dist-info/top_level.txt
didall-0.1.5.dist-info/RECORD
